Metadata-Version: 1.2
Name: qfunctions
Version: 0.0.1
Summary: Uma simples biblioteca com funções deformadas
Home-page: https://github.com/perseu912/qfunction.git
Author: Reinan Bezerra
Author-email: perseu912@gmail.com
License: MIT
Project-URL: Código fonte, https://github.com/perseu912/qfunction
Project-URL: Download, https://github.com/perseu912/qfunction/archive/main.zip
Keywords: functions q-algebra specials q-deformed
Platform: UNKNOWN
Classifier: Development Status :: 5 - Production/Stable
Classifier: Intended Audience :: Developers
Classifier: License :: OSI Approved :: MIT License
Classifier: Natural Language :: Portuguese (Brazilian)
Classifier: Operating System :: OS Independent
Classifier: Topic :: Software Development :: Internationalization
Classifier: Topic :: Scientific/Engineering :: Physics
